scons_tool_clangpp-0.2.10-py3.8-nspkg.pth
sconstool/clangpp/__init__.py
scons_tool_clangpp-0.2.10.dist-info/METADATA
scons_tool_clangpp-0.2.10.dist-info/WHEEL
scons_tool_clangpp-0.2.10.dist-info/namespace_packages.txt
scons_tool_clangpp-0.2.10.dist-info/top_level.txt
scons_tool_clangpp-0.2.10.dist-info/RECORD
